itemizer
