Metadata-Version: 1.1
Name: itemizer
Version: 1.0.1
Summary: A dmenu wrapper script
Home-page: https://github.com/seanh/itemizer
Author: Sean Hammond
Author-email: itemizer@seanh.cc
License: GPLv3
Keywords: dmenu
Platform: UNKNOWN
Classifier: Development Status :: 5 - Production/Stable
Classifier: License :: OSI Approved :: GNU General Public License v3 (GPLv3)
Classifier: Programming Language :: Python :: 2.7
